<View sceneWidth="1024" sceneHeight="768" sceneColor="0xffffff" sceneBg="" layers="1,1,0,0,第 1 层">
  <Container layers="2,1,1,0,第 2 层;1,1,1,1,第 1 层" layer="1" pWidth="100" pHeight="100">
    <Image url="png.share.bg_style3" layer="1" sizeGrid="true" pWidth="100" pHeight="100"/>
    <TextInput skin="png.share.textinput" y="200" layer="2" sizeGrid="true" height="60" size="24" color="0x0" autoSize="none" px="5" pWidth="30" x="0" name="itxtNormal"/>
    <Container layers="1,1,0" layer="2" y="110" px="5" pWidth="90" name="boxBtn" x="10">
      <Button label="label" skin="png.share.btn_green" layer="1" sizeGrid="true" labelColors="0xffffff" labelStroke="true" labelSize="24" name="btn1" x="0" y="0" pWidth="20"/>
      <Button label="label" skin="png.share.btn_green" layer="1" sizeGrid="true" labelColors="0xffffff" labelStroke="true" labelSize="24" name="btn2" pWidth="20" px="20"/>
      <Button label="label" skin="png.share.btn_green" layer="1" sizeGrid="true" labelColors="0xffffff" labelStroke="true" labelSize="24" name="btn3" pWidth="20" px="40"/>
      <Button label="label" skin="png.share.btn_green" layer="1" sizeGrid="true" labelColors="0xffffff" labelStroke="true" labelSize="24" name="btn5" pWidth="20" px="80" x="0" y="0"/>
      <Button label="label" skin="png.share.btn_red" x="0" y="0" layer="1" sizeGrid="true" labelColors="0xffffff" labelStroke="true" labelSize="24" name="btn4" px="60" pWidth="20"/>
    </Container>
    <TextInput skin="png.share.textinput" layer="2" sizeGrid="true" height="60" size="24" color="0x0" autoSize="none" px="5" pWidth="30" name="itxtPassword" py="35" asPassword="true"/>
    <Label text="label" y="210" layer="2" color="0x0" size="24" name="lbl1" width="200" height="30" centerX="0"/>
    <Label text="label" layer="2" color="0xffffff" size="30" name="lbl2" stroke="true" y="280" width="200" height="35" x="383" centerX="0"/>
  </Container>
</View>